LICENSE
MANIFEST.in
README.rst
funconf.py
setup.cfg
setup.py
funconf.egg-info/PKG-INFO
funconf.egg-info/SOURCES.txt
funconf.egg-info/dependency_links.txt
funconf.egg-info/requires.txt
funconf.egg-info/top_level.txt
tests/__init__.py
tests/test_config.py
tests/test_decorators.py